{"licenses":[{"name":"","id":0,"url":""}],"info":{"contributor":"","date_created":"","description":"","url":"","version":"","year":""},"categories":[{"id":1,"name":"Specialty Kitchen Gadgets","supercategory":""},{"id":2,"name":"Baking Supplies","supercategory":""},{"id":3,"name":"Cutting Boards","supercategory":""},{"id":4,"name":"Kitchen Carts","supercategory":""},{"id":5,"name":"Skillets","supercategory":""},{"id":6,"name":"Dinnerware","supercategory":""},{"id":7,"name":"Cabinets","supercategory":""},{"id":8,"name":"Countertops","supercategory":""},{"id":9,"name":"Faucets","supercategory":""},{"id":10,"name":"Sinks","supercategory":""},{"id":11,"name":"Wall Ovens","supercategory":""},{"id":12,"name":"Toaster Ovens","supercategory":""},{"id":13,"name":"Garbage Disposal","supercategory":""},{"id":14,"name":"Mixing Bowls","supercategory":""}],"images":[{"id":1,"width":400,"height":400,"file_name":"Wall Ovens_1.png","license":0,"flickr_url":"","coco_url":"","date_captured":0},{"id":2,"width":1025,"height":625,"file_name":"Wall Ovens_10.png","license":0,"flickr_url":"","coco_url":"","date_captured":0},{"id":3,"width":400,"height":400,"file_name":"Wall Ovens_100.png","license":0,"flickr_url":"","coco_url":"","date_captured":0},{"id":4,"width":300,"height":300,"file_name":"Wall Ovens_101.png","license":0,"flickr_url":"","coco_url":"","date_captured":0},{"id":5,"width":300,"height":300,"file_name":"Wall Ovens_102.png","license":0,"flickr_url":"","coco_url":"","date_captured":0},{"id":6,"width":480,"height":360,"file_name":"Wall Ovens_11.png","license":0,"flickr_url":"","coco_url":"","date_captured":0},{"id":7,"width":1280,"height":720,"file_name":"Wall Ovens_12.png","license":0,"flickr_url":"","coco_url":"","date_captured":0},{"id":8,"width":563,"height":678,"file_name":"Wall Ovens_13.png","license":0,"flickr_url":"","coco_url":"","date_captured":0},{"id":9,"width":600,"height":600,"file_name":"Wall Ovens_14.png","license":0,"flickr_url":"","coco_url":"","date_captured":0},{"id":10,"width":600,"height":600,"file_name":"Wall Ovens_15.png","license":0,"flickr_url":"","coco_url":"","date_captured":0},{"id":11,"width":600,"height":600,"file_name":"Wall Ovens_16.png","license":0,"flickr_url":"","coco_url":"","date_captured":0},{"id":12,"width":600,"height":600,"file_name":"Wall Ovens_17.png","license":0,"flickr_url":"","coco_url":"","date_captured":0},{"id":13,"width":600,"height":600,"file_name":"Wall Ovens_18.png","license":0,"flickr_url":"","coco_url":"","date_captured":0},{"id":14,"width":600,"height":600,"file_name":"Wall Ovens_19.png","license":0,"flickr_url":"","coco_url":"","date_captured":0},{"id":15,"width":400,"height":400,"file_name":"Wall Ovens_2.png","license":0,"flickr_url":"","coco_url":"","date_captured":0},{"id":16,"width":600,"height":600,"file_name":"Wall Ovens_20.png","license":0,"flickr_url":"","coco_url":"","date_captured":0},{"id":17,"width":600,"height":600,"file_name":"Wall Ovens_21.png","license":0,"flickr_url":"","coco_url":"","date_captured":0},{"id":18,"width":600,"height":600,"file_name":"Wall Ovens_22.png","license":0,"flickr_url":"","coco_url":"","date_captured":0},{"id":19,"width":600,"height":600,"file_name":"Wall Ovens_23.png","license":0,"flickr_url":"","coco_url":"","date_captured":0},{"id":20,"width":600,"height":600,"file_name":"Wall Ovens_24.png","license":0,"flickr_url":"","coco_url":"","date_captured":0},{"id":21,"width":600,"height":600,"file_name":"Wall Ovens_25.png","license":0,"flickr_url":"","coco_url":"","date_captured":0},{"id":22,"width":600,"height":600,"file_name":"Wall Ovens_26.png","license":0,"flickr_url":"","coco_url":"","date_captured":0},{"id":23,"width":600,"height":600,"file_name":"Wall Ovens_27.png","license":0,"flickr_url":"","coco_url":"","date_captured":0},{"id":24,"width":600,"height":600,"file_name":"Wall Ovens_28.png","license":0,"flickr_url":"","coco_url":"","date_captured":0},{"id":25,"width":300,"height":300,"file_name":"Wall Ovens_29.png","license":0,"flickr_url":"","coco_url":"","date_captured":0},{"id":26,"width":600,"height":600,"file_name":"Wall Ovens_3.png","license":0,"flickr_url":"","coco_url":"","date_captured":0},{"id":27,"width":1280,"height":720,"file_name":"Wall Ovens_30.png","license":0,"flickr_url":"","coco_url":"","date_captured":0},{"id":28,"width":400,"height":400,"file_name":"Wall Ovens_31.png","license":0,"flickr_url":"","coco_url":"","date_captured":0},{"id":29,"width":600,"height":600,"file_name":"Wall Ovens_32.png","license":0,"flickr_url":"","coco_url":"","date_captured":0},{"id":30,"width":600,"height":600,"file_name":"Wall Ovens_33.png","license":0,"flickr_url":"","coco_url":"","date_captured":0},{"id":31,"width":300,"height":300,"file_name":"Wall Ovens_34.png","license":0,"flickr_url":"","coco_url":"","date_captured":0},{"id":32,"width":300,"height":300,"file_name":"Wall Ovens_35.png","license":0,"flickr_url":"","coco_url":"","date_captured":0},{"id":33,"width":300,"height":300,"file_name":"Wall Ovens_36.png","license":0,"flickr_url":"","coco_url":"","date_captured":0},{"id":34,"width":600,"height":600,"file_name":"Wall Ovens_37.png","license":0,"flickr_url":"","coco_url":"","date_captured":0},{"id":35,"width":400,"height":400,"file_name":"Wall Ovens_38.png","license":0,"flickr_url":"","coco_url":"","date_captured":0},{"id":36,"width":300,"height":300,"file_name":"Wall Ovens_39.png","license":0,"flickr_url":"","coco_url":"","date_captured":0},{"id":37,"width":1025,"height":625,"file_name":"Wall Ovens_4.png","license":0,"flickr_url":"","coco_url":"","date_captured":0},{"id":38,"width":1000,"height":1000,"file_name":"Wall Ovens_40.png","license":0,"flickr_url":"","coco_url":"","date_captured":0},{"id":39,"width":600,"height":600,"file_name":"Wall Ovens_41.png","license":0,"flickr_url":"","coco_url":"","date_captured":0},{"id":40,"width":300,"height":300,"file_name":"Wall Ovens_42.png","license":0,"flickr_url":"","coco_url":"","date_captured":0},{"id":41,"width":600,"height":600,"file_name":"Wall Ovens_43.png","license":0,"flickr_url":"","coco_url":"","date_captured":0},{"id":42,"width":300,"height":300,"file_name":"Wall Ovens_44.png","license":0,"flickr_url":"","coco_url":"","date_captured":0},{"id":43,"width":300,"height":300,"file_name":"Wall Ovens_45.png","license":0,"flickr_url":"","coco_url":"","date_captured":0},{"id":44,"width":600,"height":600,"file_name":"Wall Ovens_46.png","license":0,"flickr_url":"","coco_url":"","date_captured":0},{"id":45,"width":300,"height":300,"file_name":"Wall Ovens_47.png","license":0,"flickr_url":"","coco_url":"","date_captured":0},{"id":46,"width":300,"height":300,"file_name":"Wall Ovens_48.png","license":0,"flickr_url":"","coco_url":"","date_captured":0},{"id":47,"width":300,"height":300,"file_name":"Wall Ovens_49.png","license":0,"flickr_url":"","coco_url":"","date_captured":0},{"id":48,"width":1025,"height":625,"file_name":"Wall Ovens_5.png","license":0,"flickr_url":"","coco_url":"","date_captured":0},{"id":49,"width":300,"height":300,"file_name":"Wall Ovens_50.png","license":0,"flickr_url":"","coco_url":"","date_captured":0},{"id":50,"width":600,"height":600,"file_name":"Wall Ovens_51.png","license":0,"flickr_url":"","coco_url":"","date_captured":0},{"id":51,"width":600,"height":600,"file_name":"Wall Ovens_52.png","license":0,"flickr_url":"","coco_url":"","date_captured":0},{"id":52,"width":300,"height":300,"file_name":"Wall Ovens_53.png","license":0,"flickr_url":"","coco_url":"","date_captured":0},{"id":53,"width":300,"height":300,"file_name":"Wall Ovens_54.png","license":0,"flickr_url":"","coco_url":"","date_captured":0},{"id":54,"width":400,"height":400,"file_name":"Wall Ovens_55.png","license":0,"flickr_url":"","coco_url":"","date_captured":0},{"id":55,"width":400,"height":400,"file_name":"Wall Ovens_56.png","license":0,"flickr_url":"","coco_url":"","date_captured":0},{"id":56,"width":600,"height":600,"file_name":"Wall Ovens_57.png","license":0,"flickr_url":"","coco_url":"","date_captured":0},{"id":57,"width":600,"height":600,"file_name":"Wall Ovens_58.png","license":0,"flickr_url":"","coco_url":"","date_captured":0},{"id":58,"width":600,"height":600,"file_name":"Wall Ovens_59.png","license":0,"flickr_url":"","coco_url":"","date_captured":0},{"id":59,"width":600,"height":600,"file_name":"Wall Ovens_6.png","license":0,"flickr_url":"","coco_url":"","date_captured":0},{"id":60,"width":300,"height":300,"file_name":"Wall Ovens_60.png","license":0,"flickr_url":"","coco_url":"","date_captured":0},{"id":61,"width":300,"height":300,"file_name":"Wall Ovens_61.png","license":0,"flickr_url":"","coco_url":"","date_captured":0},{"id":62,"width":300,"height":300,"file_name":"Wall Ovens_62.png","license":0,"flickr_url":"","coco_url":"","date_captured":0},{"id":63,"width":300,"height":300,"file_name":"Wall Ovens_63.png","license":0,"flickr_url":"","coco_url":"","date_captured":0},{"id":64,"width":600,"height":600,"file_name":"Wall Ovens_64.png","license":0,"flickr_url":"","coco_url":"","date_captured":0},{"id":65,"width":600,"height":600,"file_name":"Wall Ovens_65.png","license":0,"flickr_url":"","coco_url":"","date_captured":0},{"id":66,"width":300,"height":300,"file_name":"Wall Ovens_66.png","license":0,"flickr_url":"","coco_url":"","date_captured":0},{"id":67,"width":400,"height":400,"file_name":"Wall Ovens_67.png","license":0,"flickr_url":"","coco_url":"","date_captured":0},{"id":68,"width":300,"height":300,"file_name":"Wall Ovens_68.png","license":0,"flickr_url":"","coco_url":"","date_captured":0},{"id":69,"width":600,"height":600,"file_name":"Wall Ovens_69.png","license":0,"flickr_url":"","coco_url":"","date_captured":0},{"id":70,"width":400,"height":400,"file_name":"Wall Ovens_7.png","license":0,"flickr_url":"","coco_url":"","date_captured":0},{"id":71,"width":400,"height":400,"file_name":"Wall Ovens_70.png","license":0,"flickr_url":"","coco_url":"","date_captured":0},{"id":72,"width":2130,"height":600,"file_name":"Wall Ovens_71.png","license":0,"flickr_url":"","coco_url":"","date_captured":0},{"id":73,"width":300,"height":300,"file_name":"Wall Ovens_72.png","license":0,"flickr_url":"","coco_url":"","date_captured":0},{"id":74,"width":300,"height":300,"file_name":"Wall Ovens_73.png","license":0,"flickr_url":"","coco_url":"","date_captured":0},{"id":75,"width":300,"height":300,"file_name":"Wall Ovens_74.png","license":0,"flickr_url":"","coco_url":"","date_captured":0},{"id":76,"width":300,"height":300,"file_name":"Wall Ovens_75.png","license":0,"flickr_url":"","coco_url":"","date_captured":0},{"id":77,"width":300,"height":300,"file_name":"Wall Ovens_76.png","license":0,"flickr_url":"","coco_url":"","date_captured":0},{"id":78,"width":600,"height":600,"file_name":"Wall Ovens_77.png","license":0,"flickr_url":"","coco_url":"","date_captured":0},{"id":79,"width":300,"height":300,"file_name":"Wall Ovens_78.png","license":0,"flickr_url":"","coco_url":"","date_captured":0},{"id":80,"width":1025,"height":625,"file_name":"Wall Ovens_79.png","license":0,"flickr_url":"","coco_url":"","date_captured":0},{"id":81,"width":400,"height":400,"file_name":"Wall Ovens_8.png","license":0,"flickr_url":"","coco_url":"","date_captured":0},{"id":82,"width":300,"height":300,"file_name":"Wall Ovens_80.png","license":0,"flickr_url":"","coco_url":"","date_captured":0},{"id":83,"width":300,"height":300,"file_name":"Wall Ovens_81.png","license":0,"flickr_url":"","coco_url":"","date_captured":0},{"id":84,"width":300,"height":300,"file_name":"Wall Ovens_82.png","license":0,"flickr_url":"","coco_url":"","date_captured":0},{"id":85,"width":300,"height":300,"file_name":"Wall Ovens_83.png","license":0,"flickr_url":"","coco_url":"","date_captured":0},{"id":86,"width":300,"height":300,"file_name":"Wall Ovens_84.png","license":0,"flickr_url":"","coco_url":"","date_captured":0},{"id":87,"width":600,"height":600,"file_name":"Wall Ovens_85.png","license":0,"flickr_url":"","coco_url":"","date_captured":0},{"id":88,"width":300,"height":300,"file_name":"Wall Ovens_86.png","license":0,"flickr_url":"","coco_url":"","date_captured":0},{"id":89,"width":600,"height":600,"file_name":"Wall Ovens_87.png","license":0,"flickr_url":"","coco_url":"","date_captured":0},{"id":90,"width":400,"height":400,"file_name":"Wall Ovens_88.png","license":0,"flickr_url":"","coco_url":"","date_captured":0},{"id":91,"width":300,"height":300,"file_name":"Wall Ovens_89.png","license":0,"flickr_url":"","coco_url":"","date_captured":0},{"id":92,"width":300,"height":300,"file_name":"Wall Ovens_9.png","license":0,"flickr_url":"","coco_url":"","date_captured":0},{"id":93,"width":300,"height":300,"file_name":"Wall Ovens_90.png","license":0,"flickr_url":"","coco_url":"","date_captured":0},{"id":94,"width":300,"height":300,"file_name":"Wall Ovens_91.png","license":0,"flickr_url":"","coco_url":"","date_captured":0},{"id":95,"width":300,"height":300,"file_name":"Wall Ovens_92.png","license":0,"flickr_url":"","coco_url":"","date_captured":0},{"id":96,"width":600,"height":600,"file_name":"Wall Ovens_93.png","license":0,"flickr_url":"","coco_url":"","date_captured":0},{"id":97,"width":300,"height":300,"file_name":"Wall Ovens_94.png","license":0,"flickr_url":"","coco_url":"","date_captured":0},{"id":98,"width":600,"height":600,"file_name":"Wall Ovens_95.png","license":0,"flickr_url":"","coco_url":"","date_captured":0},{"id":99,"width":300,"height":300,"file_name":"Wall Ovens_96.png","license":0,"flickr_url":"","coco_url":"","date_captured":0},{"id":100,"width":400,"height":400,"file_name":"Wall Ovens_97.png","license":0,"flickr_url":"","coco_url":"","date_captured":0},{"id":101,"width":300,"height":300,"file_name":"Wall Ovens_98.png","license":0,"flickr_url":"","coco_url":"","date_captured":0},{"id":102,"width":400,"height":400,"file_name":"Wall Ovens_99.png","license":0,"flickr_url":"","coco_url":"","date_captured":0}],"annotations":[{"id":1,"image_id":1,"category_id":11,"segmentation":{"counts":[66,99,52,49,43,54,104,99,51,57,34,55,108,96,49,61,30,57,108,96,48,62,25,62,109,103,18,2,19,137,6,8,111,129,9,134,11,7,124,46,8,87,3,113,12,7,124,47,7,202,13,4,128,41,3,211,145,35,10,209,149,19,8,2,13,208,150,18,24,12,3,193,139,261,138,262,136,265,135,265,14,1,118,268,13,2,117,268,13,2,118,269,131,269,131,273,127,172,13,89,127,87,6,74,23,3,10,72,126,168,16,10,7,71,130,267,135,265,137,260,140,257,144,255,146,254,146,254,147,252,149,251,149,251,148,252,148,252,148,252,148,252,147,252,148,252,148,250,150,249,150,248,151,186,10,52,153,185,12,50,154,187,6,54,154,247,153,247,154,248,152,248,152,248,151,248,152,247,153,247,145,1,6,246,155,247,153,247,153,248,152,248,152,249,151,249,151,248,152,247,153,246,146,3,5,245,146,5,4,245,147,3,5,246,154,248,153,248,152,250,150,251,148,251,149,249,151,248,151,248,144,6,2,244,148,6,2,244,149,1,7,247,154,247,153,248,153,248,152,250,150,249,150,248,152,246,145,3,5,245,146,6,3,245,147,3,5,245,147,1,8,245,156,246,155,246,154,248,152,248,152,247,152,247,152,246,145,3,6,246,144,6,2,247,146,3,6,246,154,247,155,247,153,248,153,248,151,249,151,247,152,247,143,1,8,246,145,3,6,246,145,3,6,246,145,1,8,246,155,247,153,248,153,248,152,249,151,248,152,248,151,248,151,249,151,248,152,248,153,249,151,250,151,249,151,250,151,249,150,250,150,250,150,250,149,250,150,250,150,250,151,249,151,250,150,250,151,250,150,250,150,250,150,249,151,249,151,249,150,250,151,249,151,249,151,250,151,249,151,249,151,249,151,248,152,248,152,247,153,247,153,247,153,247,153,247,153,247,153,247,153,247,153,247,153,247,153,247,153,247,153,247,153,247,153,247,153,247,153,247,153,247,153,247,153,247,153,247,153,247,153,247,153,247,153,247,153,247,153,247,153,247,153,247,153,247,153,247,153,247,153,247,153,247,153,247,153,247,153,247,153,247,153,247,153,247,153,247,153,247,153,247,153,247,153,247,153,247,153,247,153,247,153,247,153,247,153,247,153,247,153,247,153,247,153,247,153,247,153,247,153,247,153,247,153,247,153,247,153,247,153,247,153,247,153,247,153,247,153,247,153,247,153,247,153,247,153,247,152,248,152,248,152,248,153,247,153,247,153,247,153,247,152,248,152,248,152,248,151,249,151,249,151,249,151,249,151,249,151,249,151,249,151,249,151,249,151,249,151,249,151,249,151,249,151,249,151,249,151,250,150,250,150,250,150,250,150,250,150,250,149,251,149,251,149,252,148,252,148,252,148,252,148,252,148,252,148,252,148,252,148,252,148,252,148,252,148,252,148,252,149,251,149,251,149,251,149,251,149,251,149,251,149,251,149,251,149,251,149,251,149,251,149,251,149,251,149,251,149,251,149,251,149,251,149,251,149,252,148,252,148,252,148,251,149,251,151,130,63,56,153,45,12,13,6,32,92,4,17,26,43654],"size":[400,400]},"area":72211.0,"bbox":[0.0,66.0,291.0,302.0],"iscrowd":1,"attributes":{"occluded":false}},{"id":2,"image_id":2,"category_id":11,"segmentation":{"counts":[169534,14,10,6,63,52,477,166,5,3,21,2,426,188,2,21,8,1,402,242,4,23,354,277,59,12,276,287,9,60,268,357,268,357,268,358,267,358,267,358,267,358,267,359,266,359,266,359,266,359,266,359,266,359,266,360,265,360,265,360,265,360,265,360,265,360,266,359,266,359,266,359,266,359,266,359,266,359,266,359,266,359,266,359,266,359,266,359,266,359,266,359,266,359,266,359,266,359,266,359,266,359,266,359,266,359,266,359,266,359,266,359,266,359,266,359,266,359,266,359,266,359,266,359,266,359,266,359,266,359,266,359,266,359,266,359,266,359,266,359,266,359,266,359,266,359,266,359,266,359,266,359,266,359,266,359,266,359,266,359,266,359,266,359,266,360,265,360,265,360,265,360,265,360,265,360,265,360,265,360,265,360,265,360,265,360,265,360,265,360,265,360,265,360,265,360,265,360,265,360,265,360,265,360,265,360,265,360,265,360,265,360,265,360,265,360,265,360,265,360,265,360,265,360,265,360,265,360,265,360,265,360,265,360,265,360,265,360,265,360,265,359,266,359,266,359,266,359,266,359,266,359,266,359,266,359,266,359,266,359,266,359,266,359,266,359,266,359,266,359,266,359,266,359,266,359,266,359,266,359,266,359,266,359,266,359,266,359,266,359,265,360,265,360,265,360,265,360,265,360,265,360,265,360,265,360,265,360,265,360,265,360,265,360,265,360,265,360,265,360,265,360,266,359,266,359,266,359,266,359,266,359,266,359,266,359,266,359,266,359,266,359,266,359,266,359,266,359,266,359,266,359,266,359,266,359,266,359,266,359,266,359,265,359,266,359,266,359,266,359,266,359,266,359,266,359,266,359,266,359,267,358,267,358,267,358,267,358,267,358,267,358,267,358,267,358,267,358,267,358,267,358,266,359,266,359,266,359,266,359,266,359,266,359,266,359,266,359,266,359,266,358,267,358,267,358,267,358,266,359,266,359,266,359,266,359,265,360,265,360,265,360,265,360,265,360,265,360,265,360,265,360,265,360,265,360,265,360,265,360,265,360,265,360,265,359,266,359,266,359,265,360,265,360,265,360,265,360,265,360,266,359,266,359,266,359,266,359,266,359,266,359,266,359,266,359,266,359,266,359,266,359,265,360,265,360,265,360,265,360,265,360,265,360,265,360,265,360,265,360,265,360,266,359,266,359,266,359,266,359,266,359,266,359,266,359,266,359,266,359,266,359,266,359,266,359,266,359,266,359,266,359,266,359,266,359,266,359,266,359,266,359,267,358,267,358,267,358,267,358,267,358,267,358,267,358,267,358,267,358,267,358,267,358,267,358,267,358,267,358,267,358,267,358,267,358,267,358,267,358,267,358,267,358,267,358,267,358,267,358,267,357,268,357,268,356,269,356,269,356,269,356,269,355,270,355,270,355,270,355,270,355,270,354,271,354,272,353,272,353,272,352,273,352,273,352,273,352,273,352,273,352,273,352,273,351,274,351,273,352,273,352,273,352,273,352,273,351,274,351,274,351,274,351,275,349,276,349,276,349,276,349,276,348,277,348,277,348,277,348,277,348,277,348,277,348,277,347,278,347,278,347,278,346,279,346,279,346,279,345,280,345,280,239,2,104,280,235,7,102,281,232,10,102,281,229,14,100,282,227,16,100,282,227,17,88,9,2,282,227,17,84,297,227,16,85,297,227,16,85,297,228,14,87,296,228,14,87,296,230,8,91,296,233,2,94,296,330,295,330,295,330,295,331,294,333,292,335,290,337,288,339,286,339,286,253,3,83,286,250,6,84,285,247,10,83,285,247,10,83,286,246,10,84,285,247,10,83,285,247,10,83,285,247,10,84,284,248,10,84,283,248,10,84,283,248,10,84,283,248,10,84,283,249,9,10,1,73,283,250,8,81,286,251,7,80,287,252,5,80,288,252,5,79,289,252,4,79,290,253,3,79,290,253,2,80,290,334,291,334,291,334,291,334,291,334,291,334,291,334,291,334,291,334,291,334,291,334,291,334,291,333,292,333,292,333,292,333,292,333,292,333,292,333,292,332,293,332,293,332,293,332,293,331,294,331,294,20,2,309,294,19,4,308,294,19,5,307,294,19,5,307,294,20,3,308,294,20,3,308,294,21,2,309,293,21,2,309,293,21,1,310,293,332,293,332,293,332,293,332,293,21,1,310,293,21,1,310,293,21,2,308,294,21,2,308,295,20,2,308,295,20,2,308,295,20,3,307,295,20,2,308,294,21,2,308,294,21,2,308,294,21,2,308,294,21,2,308,294,21,2,308,294,21,2,308,294,21,2,308,294,21,2,308,294,21,2,308,294,21,2,308,294,21,2,308,294,21,2,308,294,21,2,308,294,21,2,308,294,21,2,308,294,21,2,308,294,21,2,308,294,331,293,332,293,332,292,333,292,333,291,334,291,334,291,334,291,335,290,334,291,334,291,334,290,334,291,334,291,334,291,287,9,12,2,23,292,275,40,7,4,6,293,236,2,12,375,236,2,12,376,192,2,35,397,189,436,8,2,177,439,4,6,73,25,5,8,63,442,1,10,61,66,2,8,8,481,49,578,4,5,34,582,1,11,27,601,20,608,14,611,14,614,9,622,3,13727,1,155455],"size":[625,1025]},"area":165186.0,"bbox":[271.0,144.0,506.0,364.0],"iscrowd":1,"attributes":{"occluded":false}},{"id":3,"image_id":3,"category_id":11,"segmentation":[],"area":125230.24599999997,"bbox":[21.31,25.48,355.97,351.8],"iscrowd":0,"attributes":{"occluded":false,"rotation":0.0}},{"id":4,"image_id":4,"category_id":11,"segmentation":[[73.71,1.05,225.97,1.75,225.97,30.95,286.11,33.04,285.06,148.79,226.32,141.84,225.27,254.13,236.4,284.37,228.4,287.15,225.27,297.23,75.45,298.27,72.32,287.84,63.97,284.37,74.06,255.17,74.4,142.89,13.57,148.1,13.22,31.99,74.06,29.91]],"area":59061.0,"bbox":[13.22,1.05,272.89,297.22],"iscrowd":0,"attributes":{"occluded":false}},{"id":5,"image_id":5,"category_id":11,"segmentation":[],"area":69604.41840000001,"bbox":[16.7,21.22,266.97,260.72],"iscrowd":0,"attributes":{"occluded":false,"rotation":0.0}},{"id":6,"image_id":6,"category_id":11,"segmentation":[[309.02,127.23,394.95,125.14,394.95,281.16,309.44,293.67]],"area":13865.0,"bbox":[309.02,125.14,85.93,168.53],"iscrowd":0,"attributes":{"occluded":false}},{"id":7,"image_id":7,"category_id":11,"segmentation":[[269.69,57.93,900.0,53.71,905.05,621.67,268.84,628.41]],"area":360462.0,"bbox":[268.84,53.71,636.21,574.7],"iscrowd":0,"attributes":{"occluded":false}},{"id":8,"image_id":8,"category_id":11,"segmentation":[],"area":46359.2088,"bbox":[193.92,52.67,179.91,257.68],"iscrowd":0,"attributes":{"occluded":false,"rotation":0.0}},{"id":9,"image_id":9,"category_id":11,"segmentation":[[130.02,36.16,470.7,37.56,474.87,383.79,513.8,424.11,514.5,441.49,504.07,442.19,504.76,463.74,474.17,465.13,471.39,533.27,130.02,534.66,125.85,463.74,101.52,463.74,99.43,445.67,85.53,442.19,86.22,422.03,129.33,380.31]],"area":175373.0,"bbox":[85.53,36.16,428.97,498.5],"iscrowd":0,"attributes":{"occluded":false}},{"id":10,"image_id":10,"category_id":11,"segmentation":[],"area":213407.61600000004,"bbox":[65.37,72.32,467.2,456.78],"iscrowd":0,"attributes":{"occluded":false,"rotation":0.0}},{"id":11,"image_id":11,"category_id":11,"segmentation":[],"area":169933.98600000003,"bbox":[132.8,34.77,341.37,497.8],"iscrowd":0,"attributes":{"occluded":false,"rotation":0.0}},{"id":12,"image_id":12,"category_id":11,"segmentation":[],"area":307690.4817,"bbox":[15.31,29.21,565.93,543.69],"iscrowd":0,"attributes":{"occluded":false,"rotation":0.0}},{"id":13,"image_id":13,"category_id":11,"segmentation":[[188.42,50.07,536.74,46.59,552.04,96.65,578.46,100.13,581.24,360.15,482.51,431.76,483.21,440.1,319.13,574.29,16.0,371.97,16.7,358.06,198.85,310.09,191.9,100.13,184.25,98.04]],"area":185003.0,"bbox":[16.0,46.59,565.24,527.7],"iscrowd":0,"attributes":{"occluded":false}},{"id":14,"image_id":14,"category_id":11,"segmentation":[],"area":255466.89179999995,"bbox":[42.42,57.72,508.23,502.66],"iscrowd":0,"attributes":{"occluded":false,"rotation":0.0}},{"id":15,"image_id":15,"category_id":11,"segmentation":[],"area":98016.4034,"bbox":[25.48,78.32,316.57,309.62],"iscrowd":0,"attributes":{"occluded":false,"rotation":0.0}},{"id":16,"image_id":16,"category_id":11,"segmentation":[],"area":319062.73500000004,"bbox":[16.0,21.56,571.5,558.29],"iscrowd":0,"attributes":{"occluded":false,"rotation":0.0}},{"id":17,"image_id":17,"category_id":11,"segmentation":[],"area":209339.90310000003,"bbox":[125.16,0.71,349.71,598.61],"iscrowd":0,"attributes":{"occluded":false,"rotation":0.0}},{"id":18,"image_id":18,"category_id":11,"segmentation":[[36.16,68.84,145.32,75.1,205.11,63.28,539.52,83.44,564.55,107.08,561.77,460.27,417.86,519.36,418.55,533.96,38.95,479.04]],"area":225027.0,"bbox":[36.16,63.28,528.39,470.68],"iscrowd":0,"attributes":{"occluded":false}},{"id":19,"image_id":19,"category_id":11,"segmentation":[[61.89,63.28,444.28,50.76,447.06,100.13,510.32,102.21,512.41,116.12,520.75,114.03,529.79,154.36,561.08,159.22,558.99,458.18,432.46,557.6,62.58,452.62,61.89,182.86,55.63,181.47,54.24,167.57,61.19,167.57]],"area":216380.0,"bbox":[54.24,50.76,506.84,506.84],"iscrowd":0,"attributes":{"occluded":false}},{"id":20,"image_id":20,"category_id":11,"segmentation":[[147.4,4.18,453.31,1.4,454.01,57.72,573.59,61.89,572.2,300.36,450.53,287.84,450.53,511.02,472.78,566.64,455.4,574.98,451.92,596.54,148.79,596.54,143.23,572.9,128.63,565.94,150.88,504.07,149.49,283.67,30.6,294.8,26.43,63.97,146.71,57.02]],"area":237109.0,"bbox":[26.43,1.4,547.16,595.14],"iscrowd":0,"attributes":{"occluded":false}},{"id":21,"image_id":21,"category_id":11,"segmentation":[[33.38,14.61,465.83,72.32,444.28,580.54,26.43,598.62]],"area":232434.0,"bbox":[26.43,14.61,439.4,584.01],"iscrowd":0,"attributes":{"occluded":false}},{"id":22,"image_id":22,"category_id":11,"segmentation":[[60.5,50.76,95.96,50.76,100.13,38.95,486.69,40.34,499.9,51.46,532.57,51.46,528.4,493.64,533.27,506.85,552.04,512.41,553.43,521.45,495.03,520.06,491.55,563.86,107.08,560.38,105.69,522.84,45.9,522.14,52.16,515.19,67.45,508.93]],"area":240089.0,"bbox":[45.9,38.95,507.53,524.91],"iscrowd":0,"attributes":{"occluded":false}},{"id":23,"image_id":23,"category_id":11,"segmentation":[[12.53,134.89,324.0,133.5,326.78,191.21,586.11,207.89,588.19,466.52,322.61,420.64,323.3,431.76,15.31,431.07]],"area":156446.0,"bbox":[12.53,133.5,575.66,333.02],"iscrowd":0,"attributes":{"occluded":false}},{"id":24,"image_id":24,"category_id":11,"segmentation":[],"area":207014.37929999997,"bbox":[126.55,0.71,346.23,597.91],"iscrowd":0,"attributes":{"occluded":false,"rotation":0.0}},{"id":25,"image_id":25,"category_id":11,"segmentation":[],"area":48504.16170000001,"bbox":[65.71,6.62,167.91,288.87],"iscrowd":0,"attributes":{"occluded":false,"rotation":0.0}},{"id":26,"image_id":26,"category_id":11,"segmentation":[],"area":327239.049,"bbox":[9.05,20.87,584.7,559.67],"iscrowd":0,"attributes":{"occluded":false,"rotation":0.0}},{"id":27,"image_id":27,"category_id":11,"segmentation":{"counts":[344886,10,53,2,649,23,35,23,639,85,69,12,554,85,69,12,554,89,11,70,550,92,1,79,548,170,550,169,551,168,552,23,15,127,555,23,15,127,555,22,19,84,2,20,573,20,24,79,8,13,576,19,26,76,13,7,579,17,30,73,15,5,580,19,26,78,10,8,579,20,23,102,575,20,21,108,571,20,21,108,571,22,16,116,566,23,10,123,564,159,561,161,559,165,555,163,557,163,557,159,561,158,562,155,565,92,1,21,2,18,10,8,568,89,7,15,13,4,592,86,14,9,611,43,15,27,18,1,616,43,15,27,18,1,616,43,15,27,18,1,616,45,3,37,18,3,614,86,16,5,613,88,12,11,609,89,10,19,602,90,6,27,59,2,536,90,6,27,59,2,536,92,3,30,16,22,14,9,534,168,8,11,533,169,4,16,531,191,529,193,527,194,526,197,523,197,523,199,521,200,522,199,521,199,519,201,519,201,519,201,519,203,517,203,517,203,517,203,517,204,516,204,162,1,353,204,516,204,516,206,514,206,514,206,514,206,514,207,513,207,513,207,513,208,512,208,512,208,203,1,308,208,198,7,307,210,192,16,302,210,175,40,295,210,170,50,290,210,170,50,290,210,160,63,287,210,154,72,284,210,154,72,284,211,153,70,286,211,153,69,287,211,153,68,288,211,153,68,288,211,153,68,150,8,130,211,153,66,148,40,102,211,153,65,146,108,22,3,12,211,153,63,146,146,1,213,150,66,144,146,1,213,147,72,141,146,1,213,144,77,139,146,1,213,144,77,139,146,1,213,139,85,136,146,1,213,134,92,136,144,1,213,130,97,135,144,1,213,127,101,134,144,1,214,125,104,133,143,1,215,123,105,133,143,1,215,123,105,133,143,1,217,119,107,135,141,1,229,106,108,135,141,1,231,102,110,136,140,1,231,101,111,137,139,1,232,93,119,136,139,1,234,87,123,138,137,1,234,82,128,143,132,1,234,82,128,143,132,1,234,80,130,149,126,1,235,77,132,152,123,1,235,74,135,153,122,1,235,70,139,155,120,1,236,65,145,154,119,1,236,58,152,156,117,1,236,58,152,156,117,1,236,50,160,156,117,1,238,45,163,157,116,1,238,42,166,157,116,1,239,40,167,157,116,1,245,31,168,159,116,1,252,20,172,159,116,1,257,12,174,160,116,1,257,12,174,160,116,1,262,3,178,160,116,1,441,162,104,1,11,1,440,164,101,6,8,1,440,164,101,7,7,1,441,163,100,11,4,1,443,163,98,14,1,1,443,163,98,14,1,1,444,163,96,17,446,163,94,17,447,162,92,19,447,163,90,20,447,163,90,20,448,163,87,22,448,163,87,22,448,163,87,22,448,163,87,22,448,165,85,22,448,165,85,22,433,1,14,166,84,22,432,5,11,43,1,122,84,22,430,9,9,40,7,119,84,22,430,9,9,40,7,119,84,22,429,10,9,40,8,118,83,23,430,7,11,40,7,121,81,23,433,1,14,43,1,124,81,23,448,169,79,24,448,170,66,36,448,172,63,37,448,54,1,118,62,37,448,54,1,118,62,37,450,50,5,118,59,38,450,50,6,118,58,38,450,50,6,118,58,38,450,50,7,117,58,38,450,49,10,35,8,72,58,38,206,1,243,49,13,12,2,14,17,67,58,38,206,1,243,49,13,12,2,14,17,67,58,38,206,1,243,49,35,3,22,65,58,38,206,1,243,49,63,62,58,38,206,2,242,48,73,53,58,38,206,2,20,1,221,46,76,52,58,38,206,1,243,50,73,52,57,38,450,55,68,52,55,40,450,59,66,50,55,40,450,59,66,50,55,40,450,64,19,5,38,49,55,40,448,71,12,7,38,51,53,40,448,73,9,10,38,49,53,40,448,75,6,12,38,48,52,41,448,76,3,14,39,47,52,41,448,73,8,11,42,46,51,41,448,73,8,11,42,46,51,41,448,71,17,1,45,49,48,41,448,65,69,52,45,41,448,62,72,52,45,41,448,61,73,53,45,40,448,59,76,52,45,40,448,58,79,50,45,40,228,1,204,3,12,58,81,50,43,40,228,1,204,3,12,58,81,50,43,40,228,1,204,1,16,56,87,42,45,40,450,55,90,40,44,41,450,55,91,39,44,41,450,41,1,13,92,38,44,41,450,41,2,12,94,36,44,41,451,16,3,21,2,12,97,32,45,41,451,16,3,21,2,12,97,32,45,41,451,14,6,20,5,7,103,28,45,41,451,13,7,20,7,5,104,27,45,41,453,10,8,18,11,3,104,25,47,41,453,11,7,17,119,27,45,41,453,11,7,17,119,27,45,41,453,11,7,15,123,25,45,41,453,11,7,15,123,25,45,41,453,11,7,15,123,25,45,41,453,12,6,15,123,25,43,43,453,12,6,14,124,25,43,43,453,12,6,14,125,24,43,43,453,12,6,14,125,24,43,43,451,14,6,14,126,24,42,43,450,15,6,15,128,21,42,43,450,15,6,15,128,21,42,43,450,15,6,15,16,1,114,20,40,43,448,17,6,17,11,4,122,14,38,43,446,21,4,18,6,8,128,11,35,43,444,23,4,34,127,13,32,43,444,23,4,34,127,14,30,44,444,21,7,33,127,17,27,44,444,21,7,33,127,17,27,44,444,20,8,17,4,12,126,20,25,44,446,18,10,12,13,4,128,20,25,44,448,15,12,10,146,21,25,43,450,11,14,9,146,22,25,43,451,9,15,9,146,23,24,43,453,7,17,5,148,25,22,43,454,4,19,5,148,26,21,43,454,4,19,5,148,26,21,43,454,4,19,5,146,30,19,43,454,4,19,5,148,28,19,43,454,4,19,5,148,26,21,43,454,4,20,4,148,26,21,43,454,4,20,4,148,26,21,43,453,5,20,3,149,25,22,43,453,5,20,3,149,25,22,43,453,5,20,3,149,22,25,43,453,5,20,3,149,21,26,43,453,5,20,3,149,19,28,43,455,2,174,18,9,5,13,44,631,18,7,9,11,44,631,18,7,9,11,44,631,18,6,11,10,44,631,18,6,11,10,44,631,18,6,13,8,44,632,17,6,14,7,44,632,17,6,14,7,44,632,17,6,15,5,45,632,17,4,17,5,45,632,17,3,18,5,45,632,17,3,18,5,45,632,38,6,44,632,38,6,44,634,36,6,44,634,36,6,44,634,36,6,44,569,3,63,35,6,44,569,3,63,35,6,44,569,3,63,35,6,44,569,4,64,32,7,44,569,4,65,31,8,43,569,6,64,30,8,43,568,8,75,17,9,43,566,13,73,16,9,43,562,20,71,15,9,43,562,20,71,15,9,43,558,25,72,11,13,41,558,25,72,11,13,41,557,28,71,10,13,41,555,30,73,7,14,41,554,31,73,7,15,40,552,33,74,4,17,40,433,1,118,34,73,4,17,40,433,1,118,34,73,4,17,40,433,1,117,35,75,2,17,40,433,1,116,36,75,1,18,40,433,3,112,38,94,40,433,3,112,39,17,2,74,40,432,4,112,41,14,7,70,40,432,4,112,41,13,9,69,40,432,4,112,41,13,9,69,40,432,4,111,43,9,14,67,40,432,4,111,45,4,18,66,40,432,4,111,46,2,19,66,40,432,4,111,67,66,40,432,4,111,67,66,40,432,5,111,65,67,40,430,7,111,63,69,40,430,7,111,63,69,40,430,7,111,63,69,40,430,7,113,60,70,40,429,10,111,59,71,40,429,10,111,43,3,11,73,40,429,10,111,43,6,7,74,40,429,10,111,56,74,40,429,10,111,56,74,40,429,10,111,56,74,40,430,7,113,57,73,40,430,7,113,57,73,40,430,7,113,59,71,40,432,5,111,61,71,40,432,4,112,61,71,40,432,4,112,62,70,40,432,4,112,62,70,40,433,3,112,62,70,40,433,3,111,63,70,40,433,3,111,64,69,40,433,3,109,66,71,38,433,3,109,66,71,40,431,3,108,67,71,40,431,3,108,67,71,40,431,3,108,69,69,40,431,3,108,69,69,40,431,3,108,69,69,38,433,1,110,70,68,38,433,1,110,70,68,38,433,1,111,69,68,38,433,1,111,71,66,38,433,1,111,71,66,38,433,1,111,71,64,40,547,69,64,40,547,69,64,40,547,69,64,40,548,69,63,40,548,69,63,40,548,69,63,40,548,70,62,40,548,70,62,40,550,68,62,40,550,70,60,40,550,70,60,40,550,70,60,40,551,69,60,40,551,69,60,40,551,69,60,40,552,68,60,40,552,68,62,38,552,68,62,38,554,66,62,38,554,66,62,38,554,66,62,38,228,1,325,67,61,38,228,1,326,65,62,38,227,4,324,65,62,38,227,4,326,63,62,38,227,4,326,63,62,38,227,4,327,60,64,38,225,7,329,57,64,38,225,7,329,57,64,38,225,7,330,42,2,12,64,38,225,7,332,38,8,8,64,38,225,7,333,35,10,8,64,38,225,9,332,30,15,9,62,38,224,10,332,27,18,10,61,38,224,10,334,24,19,17,54,38,224,10,334,24,19,17,54,38,224,11,333,22,21,19,52,38,222,13,334,21,23,18,51,38,222,14,333,21,23,18,51,38,206,1,15,16,195,14,124,18,24,19,50,38,206,1,15,16,195,14,124,18,25,18,50,38,206,2,14,14,197,13,126,17,25,17,51,38,206,2,14,14,197,11,129,14,29,15,51,38,206,2,14,14,197,11,129,14,29,15,51,38,206,2,14,14,197,10,132,12,30,14,51,38,206,2,14,14,196,9,135,10,32,13,51,38,206,2,16,12,196,9,138,7,34,11,51,38,204,4,16,12,196,9,139,3,38,9,52,38,204,4,16,12,196,8,181,9,52,38,204,4,16,11,197,9,183,6,52,38,204,4,16,11,197,9,183,6,52,38,204,4,16,11,197,11,182,3,55,37,204,4,17,10,197,14,237,37,204,4,17,9,198,16,235,37,204,4,19,5,200,18,233,37,206,2,20,3,201,19,40,8,184,37,206,2,224,19,38,13,181,37,206,2,224,19,37,15,180,37,206,2,224,19,37,15,180,37,206,2,222,21,37,15,180,37,206,2,222,21,40,11,181,37,206,1,223,21,233,36,206,1,222,22,233,36,429,24,231,36,429,24,231,36,429,24,231,36,429,24,231,36,427,26,233,34,239,2,186,26,233,34,239,2,186,26,234,33,238,3,186,26,234,33,234,7,186,24,236,33,229,12,186,24,238,31,229,12,186,24,238,31,206,1,21,13,186,24,238,31,206,1,21,13,186,24,238,31,206,1,21,13,186,24,239,30,206,1,21,13,186,24,239,30,206,1,20,14,186,24,239,30,227,14,186,24,239,30,227,14,186,24,239,30,69,2,156,14,186,24,240,29,69,2,156,14,158,3,24,27,238,29,69,2,156,14,158,5,22,27,238,29,69,3,155,15,157,6,20,28,238,29,68,4,155,15,156,7,18,30,240,27,68,4,155,15,156,7,17,31,240,27,68,4,155,15,156,7,17,31,240,27,68,4,156,13,157,7,17,31,240,27,68,4,156,13,158,5,19,30,240,27,68,4,156,7,164,3,21,30,241,26,68,4,327,3,32,19,241,26,68,4,327,2,35,15,243,26,69,3,364,15,243,26,69,2,366,14,245,24,69,2,366,14,245,24,69,2,366,14,245,24,68,4,365,14,245,24,68,4,365,14,246,23,68,4,367,11,247,23,68,6,365,11,247,23,68,6,365,9,249,23,68,6,365,9,249,23,68,6,366,8,249,23,68,7,366,6,250,23,67,8,368,4,250,23,68,7,368,4,251,22,68,6,369,4,251,22,68,4,371,3,252,22,68,4,372,2,252,22,68,4,372,2,252,22,68,3,373,2,254,20,69,2,373,2,254,20,444,2,254,20,444,2,255,19,701,19,701,19,701,19,701,19,703,17,703,17,703,17,703,17,703,17,704,16,704,16,704,16,704,16,705,15,705,15,444,2,259,15,443,4,260,13,443,4,260,13,441,6,260,13,441,6,263,10,443,4,264,9,444,2,268,6,717,3,719,1,719,1,719,1,719,1,719,1,719,1,719,1,719,1,719,1,719,1,719,1,719,1,719,1,719,1,719,1,719,1,719,1,719,1,719,1,719,1,719,1,719,1,719,1,719,1,719,1,719,1,719,1,719,1,719,1,719,1,719,1,719,1,719,1,319,2,398,1,719,1,719,1,719,1,467,3,249,1,465,6,248,1,465,6,248,1,463,9,247,1,461,13,25,6,214,1,443,8,7,19,14,45,1,14,168,1,441,158,120,1,437,186,96,1,434,211,74,1,432,217,4,12,54,1,432,217,4,12,54,1,429,241,9,11,29,1,426,272,21,1,423,287,9,1,422,293,4,1,422,298,422,298,422,298,422,298,422,298,422,298,388,3,31,298,387,12,23,298,384,18,20,298,385,19,16,300,385,19,16,300,385,19,14,302,385,20,10,305,387,21,5,307,387,333,389,331,391,329,391,329,392,328,373,347,347,373,331,389,328,392,325,395,322,398,322,398,307,5,9,399,284,6,11,419,305,11,5,399,322,398,323,397,326,394,326,394,329,391,333,387,338,382,342,378,335,385,319,401,304,416,304,416,281,439,276,444,182,7,11,22,14,10,11,463,177,50,4,489,172,548,172,548,172,548,180,48,3,491,202,17,14,487,244,476,254,466,264,457,271,449,274,446,274,446,276,444,273,447,264,456,256,464,236,7,7,470,231,489,231,489,212,12,2,494,20,1,169,4,16,510,20,3,164,10,11,512,20,1,165,14,5,515,186,533,185,535,184,536,184,536,182,538,182,536,159,3,21,537,158,5,19,540,154,9,14,543,152,14,8,546,152,14,8,547,144,25,1,550,134,588,129,591,19,2,15,7,79,598,18,27,53,1,20,173,1,18,6,404,17,28,51,2,19,171,10,10,9,155197],"size":[720,1280]},"area":294512.0,"bbox":[479.0,0.0,586.0,719.0],"iscrowd":1,"attributes":{"occluded":false}},{"id":28,"image_id":28,"category_id":11,"segmentation":[],"area":128202.90000000001,"bbox":[19.92,21.31,358.75,357.36],"iscrowd":0,"attributes":{"occluded":false,"rotation":0.0}},{"id":29,"image_id":29,"category_id":11,"segmentation":[[14.61,133.5,326.78,134.89,325.39,190.51,585.41,209.98,586.8,463.05,326.08,419.94,323.3,435.24,15.31,431.07]],"area":155653.0,"bbox":[14.61,133.5,572.19,329.55],"iscrowd":0,"attributes":{"occluded":false}},{"id":30,"image_id":30,"category_id":11,"segmentation":[],"area":183943.76,"bbox":[144.62,2.1,308.0,597.22],"iscrowd":0,"attributes":{"occluded":false,"rotation":0.0}},{"id":31,"image_id":31,"category_id":11,"segmentation":[],"area":83792.2624,"bbox":[9.05,1.4,281.92,297.22],"iscrowd":0,"attributes":{"occluded":false,"rotation":0.0}},{"id":32,"image_id":32,"category_id":11,"segmentation":[[20.17,4.53,277.76,5.57,276.37,251.34,282.98,252.04,284.37,258.3,298.62,261.08,298.97,269.77,282.98,269.42,283.67,276.37,260.38,285.06,186.69,295.84,115.77,294.45,43.81,284.37,17.05,277.76,16.35,272.2,1.05,271.51,1.05,261.08,16.7,258.99,16.35,252.04,19.83,251.69]],"area":73862.0,"bbox":[1.05,4.53,297.92,291.31],"iscrowd":0,"attributes":{"occluded":false}},{"id":33,"image_id":33,"category_id":11,"segmentation":[],"area":77879.95199999999,"bbox":[6.62,13.57,285.4,272.88],"iscrowd":0,"attributes":{"occluded":false,"rotation":0.0}},{"id":34,"image_id":34,"category_id":11,"segmentation":[],"area":311525.51599999995,"bbox":[14.61,28.52,570.8,545.77],"iscrowd":0,"attributes":{"occluded":false,"rotation":0.0}},{"id":35,"image_id":35,"category_id":11,"segmentation":[],"area":150423.79499999998,"bbox":[11.11,1.38,379.14,396.75],"iscrowd":0,"attributes":{"occluded":false,"rotation":0.0}},{"id":36,"image_id":36,"category_id":11,"segmentation":[],"area":46925.8218,"bbox":[71.62,0.01,156.78,299.31],"iscrowd":0,"attributes":{"occluded":false,"rotation":0.0}},{"id":37,"image_id":37,"category_id":11,"segmentation":[[31.25,94.18,192.02,120.98,194.92,522.2,16.76,600.41,13.87,92.01]],"area":81169.0,"bbox":[13.87,92.01,181.05,508.4],"iscrowd":0,"attributes":{"occluded":false}},{"id":38,"image_id":38,"category_id":11,"segmentation":[],"area":573326.0295000001,"bbox":[25.53,200.5,947.85,604.87],"iscrowd":0,"attributes":{"occluded":false,"rotation":0.0}},{"id":39,"image_id":39,"category_id":11,"segmentation":[[164.09,2.79,437.32,3.49,438.02,54.24,432.46,54.94,431.07,273.24,454.7,314.96,456.79,329.56,433.85,332.34,431.07,501.29,455.4,570.12,454.01,591.67,146.71,590.97,144.62,570.81,168.26,495.03,166.18,337.21,140.45,335.82,143.93,318.44,170.35,266.99]],"area":160359.0,"bbox":[140.45,2.79,316.34,588.88],"iscrowd":0,"attributes":{"occluded":false}},{"id":40,"image_id":40,"category_id":11,"segmentation":[],"area":67079.10440000001,"bbox":[12.53,19.48,275.66,243.34],"iscrowd":0,"attributes":{"occluded":false,"rotation":0.0}},{"id":41,"image_id":41,"category_id":11,"segmentation":[[148.1,4.18,452.62,3.49,452.62,56.33,570.12,63.28,568.73,297.58,453.31,286.45,449.84,504.07,474.17,568.73,457.49,577.07,449.84,594.45,147.4,595.84,143.23,572.2,130.72,568.03,130.72,558.3,150.88,506.15,148.1,286.45,29.21,296.88,29.91,60.5,147.4,57.72]],"area":235619.0,"bbox":[29.21,3.49,540.91,592.35],"iscrowd":0,"attributes":{"occluded":false}},{"id":42,"image_id":42,"category_id":11,"segmentation":[],"area":58504.04999999999,"bbox":[31.65,18.44,236.38,247.5],"iscrowd":0,"attributes":{"occluded":false,"rotation":0.0}},{"id":43,"image_id":43,"category_id":11,"segmentation":[],"area":57501.32479999999,"bbox":[42.07,21.22,221.44,259.67],"iscrowd":0,"attributes":{"occluded":false,"rotation":0.0}},{"id":44,"image_id":44,"category_id":11,"segmentation":[],"area":305074.5146,"bbox":[20.17,27.82,558.98,545.77],"iscrowd":0,"attributes":{"occluded":false,"rotation":0.0}},{"id":45,"image_id":45,"category_id":11,"segmentation":[[22.26,9.75,274.29,10.79,272.2,240.22,298.97,259.69,300.0,266.65,300.0,269.07,284.72,268.73,227.36,282.98,153.31,290.63,44.86,279.15,0.36,269.07,1.4,257.25,21.56,238.48]],"area":69590.0,"bbox":[0.36,9.75,299.64,280.88],"iscrowd":0,"attributes":{"occluded":false}},{"id":46,"image_id":46,"category_id":11,"segmentation":[],"area":84802.9936,"bbox":[8.7,0.36,283.66,298.96],"iscrowd":0,"attributes":{"occluded":false,"rotation":0.0}},{"id":47,"image_id":47,"category_id":11,"segmentation":[],"area":78008.1372,"bbox":[8.7,13.22,282.27,276.36],"iscrowd":0,"attributes":{"occluded":false,"rotation":0.0}},{"id":48,"image_id":48,"category_id":11,"segmentation":[],"area":150676.5046,"bbox":[272.41,228.89,481.61,312.86],"iscrowd":0,"attributes":{"occluded":false,"rotation":0.0}},{"id":49,"image_id":49,"category_id":11,"segmentation":[],"area":71049.7656,"bbox":[13.57,21.22,272.88,260.37],"iscrowd":0,"attributes":{"occluded":false,"rotation":0.0}},{"id":50,"image_id":50,"category_id":11,"segmentation":[],"area":111360.3,"bbox":[111.25,141.84,337.2,330.25],"iscrowd":0,"attributes":{"occluded":false,"rotation":0.0}},{"id":51,"image_id":51,"category_id":11,"segmentation":[],"area":29535.120000000003,"bbox":[207.89,251.69,190.5,155.04],"iscrowd":0,"attributes":{"occluded":false,"rotation":0.0}},{"id":52,"image_id":52,"category_id":11,"segmentation":[[15.31,29.21,261.08,28.86,262.12,40.34,228.05,50.07,238.13,112.29,246.48,112.99,252.39,100.48,260.38,118.55,261.08,272.9,14.26,271.16]],"area":58008.0,"bbox":[14.26,28.86,247.86,244.04],"iscrowd":0,"attributes":{"occluded":false}},{"id":53,"image_id":53,"category_id":11,"segmentation":[],"area":53841.073200000006,"bbox":[32.34,41.73,233.26,230.82],"iscrowd":0,"attributes":{"occluded":false,"rotation":0.0}},{"id":54,"image_id":54,"category_id":11,"segmentation":[],"area":131173.3686,"bbox":[15.75,17.6,368.02,356.43],"iscrowd":0,"attributes":{"occluded":false,"rotation":0.0}},{"id":55,"image_id":55,"category_id":11,"segmentation":[],"area":81480.8736,"bbox":[87.59,10.19,217.84,374.04],"iscrowd":0,"attributes":{"occluded":false,"rotation":0.0}},{"id":56,"image_id":56,"category_id":11,"segmentation":[],"area":227357.1944,"bbox":[102.91,16.0,399.77,568.72],"iscrowd":0,"attributes":{"occluded":false,"rotation":0.0}},{"id":57,"image_id":57,"category_id":11,"segmentation":[[13.92,0.71,588.89,0.71,588.19,598.62,504.76,599.32,502.68,483.21,93.87,482.51,93.17,599.32,12.53,599.32]],"area":296350.0,"bbox":[12.53,0.71,576.36,598.61],"iscrowd":0,"attributes":{"occluded":false}},{"id":58,"image_id":58,"category_id":11,"segmentation":[],"area":28268.8749,"bbox":[212.76,221.8,174.51,161.99],"iscrowd":0,"attributes":{"occluded":false,"rotation":0.0}},{"id":59,"image_id":59,"category_id":11,"segmentation":[[134.19,11.83,468.61,11.14,467.22,589.58,131.41,586.8]],"area":193212.0,"bbox":[131.41,11.14,337.2,578.44],"iscrowd":0,"attributes":{"occluded":false}},{"id":60,"image_id":60,"category_id":11,"segmentation":[],"area":46305.124800000005,"bbox":[67.1,9.4,165.47,279.84],"iscrowd":0,"attributes":{"occluded":false,"rotation":0.0}},{"id":61,"image_id":61,"category_id":11,"segmentation":[[73.01,1.75,226.32,1.05,227.71,27.82,284.72,30.6,285.76,148.45,225.97,141.84,225.27,254.82,235.01,281.24,229.1,286.8,225.97,298.27,74.4,297.93,71.97,285.76,64.67,284.02,63.63,274.29,74.06,252.73,74.06,143.58,14.26,147.4,13.57,30.95,73.36,28.86]],"area":59300.0,"bbox":[13.57,1.05,272.19,297.22],"iscrowd":0,"attributes":{"occluded":false}},{"id":62,"image_id":62,"category_id":11,"segmentation":[],"area":47702.0576,"bbox":[69.54,0.36,159.56,298.96],"iscrowd":0,"attributes":{"occluded":false,"rotation":0.0}},{"id":63,"image_id":63,"category_id":11,"segmentation":[[32.34,8.7,268.03,8.7,265.94,216.93,293.75,271.51,292.02,283.67,163.4,292.02,7.66,284.72,6.96,269.42,35.12,214.84]],"area":67413.0,"bbox":[6.96,8.7,286.79,283.32],"iscrowd":0,"attributes":{"occluded":false}},{"id":64,"image_id":64,"category_id":11,"segmentation":[[164.79,0.01,440.8,2.79,430.37,273.24,456.1,312.18,452.62,330.25,434.54,334.43,433.85,499.9,456.1,571.51,454.01,589.58,146.71,589.58,143.23,568.03,166.18,493.64,167.57,332.34,146.01,331.65,143.23,311.48,165.48,266.29]],"area":162570.0,"bbox":[143.23,0.01,312.87,589.57],"iscrowd":0,"attributes":{"occluded":false}},{"id":65,"image_id":65,"category_id":11,"segmentation":[],"area":204513.2925,"bbox":[128.63,5.57,344.85,593.05],"iscrowd":0,"attributes":{"occluded":false,"rotation":0.0}},{"id":66,"image_id":66,"category_id":11,"segmentation":[[92.48,14.61,208.24,14.61,206.85,262.12,213.8,278.11,196.07,280.2,144.97,288.19,98.04,280.2,86.92,279.85,93.17,254.13]],"area":30899.0,"bbox":[86.92,14.61,126.88,273.58],"iscrowd":0,"attributes":{"occluded":false}},{"id":67,"image_id":67,"category_id":11,"segmentation":[],"area":62488.54440000001,"bbox":[114.01,18.06,171.96,363.39],"iscrowd":0,"attributes":{"occluded":false,"rotation":0.0}},{"id":68,"image_id":68,"category_id":11,"segmentation":[],"area":88022.83800000003,"bbox":[0.71,4.53,298.95,294.44],"iscrowd":0,"attributes":{"occluded":false,"rotation":0.0}},{"id":69,"image_id":69,"category_id":11,"segmentation":[[64.67,36.86,537.44,36.86,531.88,452.62,579.15,519.36,534.66,520.06,535.35,561.77,63.97,563.86,66.06,516.58,27.13,520.06,63.97,452.62]],"area":249945.0,"bbox":[27.13,36.86,552.02,527.0],"iscrowd":0,"attributes":{"occluded":false}},{"id":70,"image_id":70,"category_id":11,"segmentation":[],"area":77289.15039999998,"bbox":[9.26,31.97,231.28,334.18],"iscrowd":0,"attributes":{"occluded":false,"rotation":0.0}},{"id":71,"image_id":71,"category_id":11,"segmentation":[],"area":131296.099,"bbox":[14.82,18.06,371.26,353.65],"iscrowd":0,"attributes":{"occluded":false,"rotation":0.0}},{"id":72,"image_id":72,"category_id":11,"segmentation":[[190.73,59.48,502.03,59.48,502.03,544.66,159.88,540.45,166.89,167.45,193.54,164.65,197.74,132.4,193.54,100.15,173.9,94.54]],"area":160838.0,"bbox":[159.88,59.48,342.15,485.18],"iscrowd":0,"attributes":{"occluded":false}},{"id":73,"image_id":72,"category_id":11,"segmentation":[],"area":178753.56420000002,"bbox":[875.02,86.12,363.18,492.19],"iscrowd":0,"attributes":{"occluded":false,"rotation":0.0}},{"id":74,"image_id":73,"category_id":11,"segmentation":[],"area":82160.33200000001,"bbox":[1.4,12.53,296.18,277.4],"iscrowd":0,"attributes":{"occluded":false,"rotation":0.0}},{"id":75,"image_id":74,"category_id":11,"segmentation":[],"area":46509.7809,"bbox":[71.62,0.01,155.39,299.31],"iscrowd":0,"attributes":{"occluded":false,"rotation":0.0}},{"id":76,"image_id":75,"category_id":11,"segmentation":[[69.54,73.01,230.14,72.32,232.22,101.87,287.5,102.91,286.11,225.97,229.79,218.32,230.14,226.66,74.06,227.36,71.97,219.02,12.53,224.58,12.53,101.52,69.88,102.91]],"area":38306.0,"bbox":[12.53,72.32,274.97,155.04],"iscrowd":0,"attributes":{"occluded":false}},{"id":77,"image_id":76,"category_id":11,"segmentation":[],"area":72332.0542,"bbox":[11.83,20.17,277.06,261.07],"iscrowd":0,"attributes":{"occluded":false,"rotation":0.0}},{"id":78,"image_id":77,"category_id":11,"segmentation":[],"area":54207.88050000001,"bbox":[30.95,33.04,239.17,226.65],"iscrowd":0,"attributes":{"occluded":false,"rotation":0.0}},{"id":79,"image_id":78,"category_id":11,"segmentation":[],"area":283790.00560000003,"bbox":[27.82,42.42,547.16,518.66],"iscrowd":0,"attributes":{"occluded":false,"rotation":0.0}},{"id":80,"image_id":79,"category_id":11,"segmentation":[],"area":65085.035599999996,"bbox":[41.38,0.71,217.96,298.61],"iscrowd":0,"attributes":{"occluded":false,"rotation":0.0}},{"id":81,"image_id":80,"category_id":11,"segmentation":[],"area":125607.95120000004,"bbox":[308.62,176.02,362.84,346.18],"iscrowd":0,"attributes":{"occluded":false,"rotation":0.0}},{"id":82,"image_id":81,"category_id":11,"segmentation":[],"area":62712.86679999999,"bbox":[8.33,34.75,188.18,333.26],"iscrowd":0,"attributes":{"occluded":false,"rotation":0.0}},{"id":83,"image_id":82,"category_id":11,"segmentation":[],"area":56521.9395,"bbox":[28.86,23.3,241.95,233.61],"iscrowd":0,"attributes":{"occluded":false,"rotation":0.0}},{"id":84,"image_id":83,"category_id":11,"segmentation":[],"area":81650.0349,"bbox":[8.7,1.4,284.01,287.49],"iscrowd":0,"attributes":{"occluded":false,"rotation":0.0}},{"id":85,"image_id":84,"category_id":11,"segmentation":[],"area":70067.24519999999,"bbox":[14.96,19.48,267.32,262.11],"iscrowd":0,"attributes":{"occluded":false,"rotation":0.0}},{"id":86,"image_id":85,"category_id":11,"segmentation":[],"area":55750.1874,"bbox":[39.64,25.74,222.13,250.98],"iscrowd":0,"attributes":{"occluded":false,"rotation":0.0}},{"id":87,"image_id":86,"category_id":11,"segmentation":[],"area":56203.368,"bbox":[30.25,22.95,239.52,234.65],"iscrowd":0,"attributes":{"occluded":false,"rotation":0.0}},{"id":88,"image_id":87,"category_id":11,"segmentation":[],"area":38735.56589999999,"bbox":[317.05,91.78,147.39,262.81],"iscrowd":0,"attributes":{"occluded":false,"rotation":0.0}},{"id":89,"image_id":88,"category_id":11,"segmentation":[],"area":49076.181,"bbox":[36.51,42.77,227.7,215.53],"iscrowd":0,"attributes":{"occluded":false,"rotation":0.0}},{"id":90,"image_id":89,"category_id":11,"segmentation":[],"area":130323.25500000002,"bbox":[104.99,57.02,396.3,328.85],"iscrowd":0,"attributes":{"occluded":false,"rotation":0.0}},{"id":91,"image_id":90,"category_id":11,"segmentation":[],"area":143921.0434,"bbox":[10.65,12.04,381.46,377.29],"iscrowd":0,"attributes":{"occluded":false,"rotation":0.0}},{"id":92,"image_id":91,"category_id":11,"segmentation":[],"area":53581.629199999996,"bbox":[61.19,0.71,180.07,297.56],"iscrowd":0,"attributes":{"occluded":false,"rotation":0.0}},{"id":93,"image_id":92,"category_id":11,"segmentation":[],"area":52756.18530000001,"bbox":[61.54,1.4,177.29,297.57],"iscrowd":0,"attributes":{"occluded":false,"rotation":0.0}},{"id":94,"image_id":93,"category_id":11,"segmentation":[[36.51,47.64,65.02,47.98,65.37,44.51,219.02,41.38,218.67,188.77,282.28,210.67,285.06,218.32,290.97,223.19,270.12,224.58,270.46,234.66,138.37,258.99,137.67,247.87,123.07,251.34,36.51,190.16,31.3,63.97]],"area":37939.0,"bbox":[31.3,41.38,259.67,217.61],"iscrowd":0,"attributes":{"occluded":false}},{"id":95,"image_id":94,"category_id":11,"segmentation":[],"area":62246.8656,"bbox":[22.61,33.04,256.54,242.64],"iscrowd":0,"attributes":{"occluded":false,"rotation":0.0}},{"id":96,"image_id":95,"category_id":11,"segmentation":[],"area":82647.29,"bbox":[9.05,2.1,277.75,297.56],"iscrowd":0,"attributes":{"occluded":false,"rotation":0.0}},{"id":97,"image_id":96,"category_id":11,"segmentation":[],"area":208682.5482,"bbox":[125.85,0.71,349.02,597.91],"iscrowd":0,"attributes":{"occluded":false,"rotation":0.0}},{"id":98,"image_id":97,"category_id":11,"segmentation":[],"area":83182.75559999999,"bbox":[10.79,1.75,280.53,296.52],"iscrowd":0,"attributes":{"occluded":false,"rotation":0.0}},{"id":99,"image_id":98,"category_id":11,"segmentation":[[147.4,2.1,449.84,4.18,449.14,272.55,474.17,315.65,471.39,324.0,471.39,330.25,453.31,331.65,450.53,501.29,476.26,574.29,474.87,581.24,472.09,588.19,332.34,597.23,149.49,593.75,132.8,585.41,130.02,574.29,129.33,568.03,153.66,491.55,148.79,331.65,136.28,332.34,130.02,309.4,153.66,266.99]],"area":181299.0,"bbox":[129.33,2.1,346.93,595.13],"iscrowd":0,"attributes":{"occluded":false}},{"id":100,"image_id":99,"category_id":11,"segmentation":[],"area":39327.235400000005,"bbox":[75.1,11.83,152.26,258.29],"iscrowd":0,"attributes":{"occluded":false,"rotation":0.0}},{"id":101,"image_id":100,"category_id":11,"segmentation":[],"area":146566.3941,"bbox":[9.72,1.84,380.07,385.63],"iscrowd":0,"attributes":{"occluded":false,"rotation":0.0}},{"id":102,"image_id":101,"category_id":11,"segmentation":[[28.86,18.44,268.38,17.05,274.63,263.51,255.52,266.64,173.48,288.19,126.55,289.24,40.68,264.21,27.47,262.82,27.82,246.48,30.25,244.39]],"area":63012.0,"bbox":[27.47,17.05,247.16,272.19],"iscrowd":0,"attributes":{"occluded":false}},{"id":103,"image_id":102,"category_id":11,"segmentation":[],"area":138447.78,"bbox":[9.72,17.6,381.0,363.38],"iscrowd":0,"attributes":{"occluded":false,"rotation":0.0}}]}